{
  "project_info": {
    "project_number": "731165738089",
    "project_id": "todolist-2fa08",
    "storage_bucket": "todolist-2fa08.firebasestorage.app"
  },
  "client": [
    {
      "client_info": {
        "mobilesdk_app_id": "1:731165738089:android:5a0e645e6680faa5998ef8",
        "android_client_info": {
          "package_name": "com.example.todo_list_firebase"
        }
      },
      "oauth_client": [],
      "api_key": [
        {
          "current_key": "AIzaSyBFtaosnsvo-ieI7e5uLiNqNaYY7E7f7ms"
        }
      ],
      "services": {
        "appinvite_service": {
          "other_platform_oauth_client": []
        }
      }
    }
  ],
  "configuration_version": "1"
}